<instrumentationManifest xmlns="http://schemas.microsoft.com/win/2004/08/events">
 <instrumentation xmlns:xs="http://www.w3.org/2001/XMLSchema" xmlns:xsi="http://www.w3.org/2001/XMLSchema-instance" xmlns:win="http://manifests.microsoft.com/win/2004/08/windows/events">
  <events>
   <provider name="Microsoft-User Experience Virtualization-SQM Uploader" guid="{57003e21-269b-4bdc-8434-b3bf8d57d2d5}" resourceFileName="Microsoft-User Experience Virtualization-SQM Uploader" messageFileName="Microsoft-User Experience Virtualization-SQM Uploader" symbol="MicrosoftUserExperienceVirtualizationSQMUploader" source="Xml" >
    <keywords>
    </keywords>
    <tasks>
     <task name="task_0" message="$(string.task_task_0)" value="0"/>
    </tasks>
    <events>
     <event value="1" symbol="task_0Start" version="0" task="task_0" opcode="win:Start" level="win:Informational"/>
     <event value="2" symbol="task_0" version="0" task="task_0" level="win:Informational"/>
     <event value="3" symbol="task_03" version="0" task="task_0" level="win:Error" template="task_03Args"/>
     <event value="4" symbol="task_04" version="0" task="task_0" level="win:Error" template="task_04Args"/>
     <event value="5" symbol="task_05" version="0" task="task_0" level="win:Informational"/>
     <event value="6" symbol="task_06" version="0" task="task_0" level="win:Verbose" template="task_06Args"/>
     <event value="7" symbol="task_07" version="0" task="task_0" level="win:Warning" template="task_06Args"/>
     <event value="8" symbol="task_08" version="0" task="task_0" level="win:Error" template="task_08Args"/>
     <event value="9" symbol="task_09" version="0" task="task_0" level="win:Informational"/>
     <event value="10" symbol="task_010" version="0" task="task_0" level="win:Error" template="task_010Args"/>
     <event value="11" symbol="task_011" version="0" task="task_0" level="win:Error"/>
     <event value="12" symbol="task_012" version="0" task="task_0" level="win:Informational" template="task_012Args"/>
     <event value="13" symbol="task_013" version="0" task="task_0" level="win:Informational" template="task_04Args"/>
     <event value="14" symbol="task_014" version="0" task="task_0" level="win:Critical" template="task_08Args"/>
     <event value="108" symbol="task_0108" version="0" task="task_0" level="win:Warning"/>
     <event value="268" symbol="task_0268" version="0" task="task_0" level="win:Informational"/>
     <event value="2566" symbol="task_02566" version="0" task="task_0" level="win:Always"/>
    </events>
    <templates>
     <template tid="task_03Args">
      <data name="hresult" inType="win:UInt32"/>
     </template>
     <template tid="task_04Args">
      <data name="WString1" inType="win:UnicodeString"/>
     </template>
     <template tid="task_06Args">
      <data name="hr" inType="win:UInt32"/>
      <data name="filename" inType="win:UnicodeString"/>
      <data name="http" inType="win:Int32"/>
     </template>
     <template tid="task_08Args">
      <data name="error" inType="win:UInt32"/>
     </template>
     <template tid="task_010Args">
      <data name="String1" inType="win:AnsiString"/>
     </template>
     <template tid="task_012Args">
      <data name="uint32" inType="win:UInt32"/>
     </template>
    </templates>
   </provider>
  </events>
 </instrumentation>
 <localization>
  <resources culture="en-US">
   <stringTable>
    <string id="task_task_0" value="task_0"/>
   </stringTable>
  </resources>
 </localization>
</instrumentationManifest>
