<instrumentationManifest xmlns="http://schemas.microsoft.com/win/2004/08/events">
 <instrumentation xmlns:xs="http://www.w3.org/2001/XMLSchema" xmlns:xsi="http://www.w3.org/2001/XMLSchema-instance" xmlns:win="http://manifests.microsoft.com/win/2004/08/windows/events">
  <events>
   <provider name="Microsoft-Windows-Search" guid="{ca4e628d-8567-4896-ab6b-835b221f373f}" resourceFileName="Microsoft-Windows-Search" messageFileName="Microsoft-Windows-Search" symbol="MicrosoftWindowsSearch" source="Xml" >
    <keywords>
    </keywords>
    <tasks>
     <task name="task_0" message="$(string.task_task_0)" value="0">
>
      <opcodes>
       <opcode name="opcode_64" message="$(string.opcode_task_0opcode_64)" value="64"/>
       <opcode name="opcode_128" message="$(string.opcode_task_0opcode_128)" value="128"/>
       <opcode name="opcode_192" message="$(string.opcode_task_0opcode_192)" value="192"/>
      </opcodes>
     </task>
    </tasks>
    <events>
     <event value="1003" symbol="task_0PCODE_64pcode_64" version="0" task="task_0" opcode="opcode_64" level="win:Always" template="task_0PCODE_64pcode_64Args"/>
     <event value="1004" symbol="task_0PCODE_64pcode_641004" version="0" task="task_0" opcode="opcode_64" level="win:Always" template="task_0PCODE_64pcode_641004Args"/>
     <event value="1005" symbol="task_0PCODE_64pcode_641005" version="0" task="task_0" opcode="opcode_64" level="win:Always" template="task_0PCODE_64pcode_64Args"/>
     <event value="1006" symbol="task_0PCODE_192pcode_192" version="0" task="task_0" opcode="opcode_192" level="win:Always" template="task_0PCODE_192pcode_192Args"/>
     <event value="1007" symbol="task_0PCODE_192pcode_1921007" version="0" task="task_0" opcode="opcode_192" level="win:Always" template="task_0PCODE_64pcode_64Args"/>
     <event value="1008" symbol="task_0PCODE_128pcode_128" version="0" task="task_0" opcode="opcode_128" level="win:Always" template="task_0PCODE_64pcode_641004Args"/>
     <event value="1009" symbol="task_0PCODE_192pcode_1921009" version="0" task="task_0" opcode="opcode_192" level="win:Always" template="task_0PCODE_192pcode_1921009Args"/>
     <event value="1010" symbol="task_0PCODE_64pcode_641010" version="0" task="task_0" opcode="opcode_64" level="win:Always" template="task_0PCODE_64pcode_64Args"/>
     <event value="1011" symbol="task_0PCODE_192pcode_1921011" version="0" task="task_0" opcode="opcode_192" level="win:Always" template="task_0PCODE_192pcode_1921011Args"/>
     <event value="1013" symbol="task_0PCODE_64pcode_641013" version="0" task="task_0" opcode="opcode_64" level="win:Always" template="task_0PCODE_64pcode_64Args"/>
     <event value="1014" symbol="task_0PCODE_128pcode_1281014" version="0" task="task_0" opcode="opcode_128" level="win:Always" template="task_0PCODE_128pcode_1281014Args"/>
     <event value="1015" symbol="task_0PCODE_128pcode_1281015" version="0" task="task_0" opcode="opcode_128" level="win:Always" template="task_0PCODE_128pcode_1281015Args"/>
     <event value="1016" symbol="task_0PCODE_192pcode_1921016" version="0" task="task_0" opcode="opcode_192" level="win:Always" template="task_0PCODE_192pcode_1921016Args"/>
     <event value="1017" symbol="task_0PCODE_64pcode_641017" version="0" task="task_0" opcode="opcode_64" level="win:Always" template="task_0PCODE_64pcode_641017Args"/>
     <event value="1018" symbol="task_0PCODE_128pcode_1281018" version="0" task="task_0" opcode="opcode_128" level="win:Always" template="task_0PCODE_192pcode_1921016Args"/>
     <event value="1019" symbol="task_0PCODE_192pcode_1921019" version="0" task="task_0" opcode="opcode_192" level="win:Always" template="task_0PCODE_192pcode_1921019Args"/>
     <event value="1044" symbol="task_0PCODE_128pcode_1281044" version="0" task="task_0" opcode="opcode_128" level="win:Always" template="task_0PCODE_128pcode_1281044Args"/>
     <event value="1053" symbol="task_0PCODE_128pcode_1281053" version="0" task="task_0" opcode="opcode_128" level="win:Always" template="task_0PCODE_128pcode_1281053Args"/>
     <event value="3003" symbol="task_0PCODE_192pcode_1923003" version="0" task="task_0" opcode="opcode_192" level="win:Always" template="task_0PCODE_64pcode_64Args"/>
     <event value="3006" symbol="task_0PCODE_192pcode_1923006" version="0" task="task_0" opcode="opcode_192" level="win:Always" template="task_0PCODE_64pcode_64Args"/>
     <event value="3007" symbol="task_0PCODE_192pcode_1923007" version="0" task="task_0" opcode="opcode_192" level="win:Always" template="task_0PCODE_64pcode_64Args"/>
     <event value="3008" symbol="task_0PCODE_192pcode_1923008" version="0" task="task_0" opcode="opcode_192" level="win:Always" template="task_0PCODE_192pcode_1923008Args"/>
     <event value="3009" symbol="task_0PCODE_192pcode_1923009" version="0" task="task_0" opcode="opcode_192" level="win:Always" template="task_0PCODE_64pcode_64Args"/>
     <event value="3010" symbol="task_0PCODE_192pcode_1923010" version="0" task="task_0" opcode="opcode_192" level="win:Always" template="task_0PCODE_192pcode_1923010Args"/>
     <event value="3011" symbol="task_0PCODE_192pcode_1923011" version="0" task="task_0" opcode="opcode_192" level="win:Always" template="task_0PCODE_192pcode_1923010Args"/>
     <event value="3013" symbol="task_0PCODE_192pcode_1923013" version="0" task="task_0" opcode="opcode_192" level="win:Always" template="task_0PCODE_192pcode_1923008Args"/>
     <event value="3014" symbol="task_0PCODE_192pcode_1923014" version="0" task="task_0" opcode="opcode_192" level="win:Always" template="task_0PCODE_192pcode_1923014Args"/>
     <event value="3015" symbol="task_0PCODE_192pcode_1923015" version="0" task="task_0" opcode="opcode_192" level="win:Always" template="task_0PCODE_64pcode_64Args"/>
     <event value="3020" symbol="task_0PCODE_192pcode_1923020" version="0" task="task_0" opcode="opcode_192" level="win:Always" template="task_0PCODE_192pcode_1923020Args"/>
     <event value="3023" symbol="task_0PCODE_128pcode_1283023" version="0" task="task_0" opcode="opcode_128" level="win:Always" template="task_0PCODE_64pcode_64Args"/>
     <event value="3024" symbol="task_0PCODE_128pcode_1283024" version="0" task="task_0" opcode="opcode_128" level="win:Always" template="task_0PCODE_64pcode_64Args"/>
     <event value="3025" symbol="task_0PCODE_192pcode_1923025" version="0" task="task_0" opcode="opcode_192" level="win:Always" template="task_0PCODE_192pcode_1923020Args"/>
     <event value="3026" symbol="task_0PCODE_192pcode_1923026" version="0" task="task_0" opcode="opcode_192" level="win:Always" template="task_0PCODE_64pcode_64Args"/>
     <event value="3027" symbol="task_0PCODE_192pcode_1923027" version="0" task="task_0" opcode="opcode_192" level="win:Always" template="task_0PCODE_192pcode_1923027Args"/>
     <event value="3028" symbol="task_0PCODE_192pcode_1923028" version="0" task="task_0" opcode="opcode_192" level="win:Always" template="task_0PCODE_64pcode_64Args"/>
     <event value="3029" symbol="task_0PCODE_192pcode_1923029" version="0" task="task_0" opcode="opcode_192" level="win:Always" template="task_0PCODE_192pcode_1923029Args"/>
     <event value="3030" symbol="task_0PCODE_192pcode_1923030" version="0" task="task_0" opcode="opcode_192" level="win:Always" template="task_0PCODE_64pcode_64Args"/>
     <event value="3031" symbol="task_0PCODE_192pcode_1923031" version="0" task="task_0" opcode="opcode_192" level="win:Always" template="task_0PCODE_64pcode_64Args"/>
     <event value="3032" symbol="task_0PCODE_192pcode_1923032" version="0" task="task_0" opcode="opcode_192" level="win:Always" template="task_0PCODE_64pcode_64Args"/>
     <event value="3033" symbol="task_0PCODE_192pcode_1923033" version="0" task="task_0" opcode="opcode_192" level="win:Always" template="task_0PCODE_64pcode_64Args"/>
     <event value="3034" symbol="task_0PCODE_192pcode_1923034" version="0" task="task_0" opcode="opcode_192" level="win:Always" template="task_0PCODE_192pcode_1923034Args"/>
     <event value="3036" symbol="task_0PCODE_128pcode_1283036" version="0" task="task_0" opcode="opcode_128" level="win:Always" template="task_0PCODE_192pcode_1923027Args"/>
     <event value="3037" symbol="task_0PCODE_128pcode_1283037" version="0" task="task_0" opcode="opcode_128" level="win:Always" template="task_0PCODE_192pcode_1923027Args"/>
     <event value="3038" symbol="task_0PCODE_128pcode_1283038" version="0" task="task_0" opcode="opcode_128" level="win:Always" template="task_0PCODE_128pcode_1283038Args"/>
     <event value="3039" symbol="task_0PCODE_128pcode_1283039" version="0" task="task_0" opcode="opcode_128" level="win:Always" template="task_0PCODE_64pcode_64Args"/>
     <event value="3040" symbol="task_0PCODE_192pcode_1923040" version="0" task="task_0" opcode="opcode_192" level="win:Always" template="task_0PCODE_192pcode_1923040Args"/>
     <event value="3041" symbol="task_0PCODE_64pcode_643041" version="0" task="task_0" opcode="opcode_64" level="win:Always" template="task_0PCODE_64pcode_64Args"/>
     <event value="3042" symbol="task_0PCODE_128pcode_1283042" version="0" task="task_0" opcode="opcode_128" level="win:Always" template="task_0PCODE_64pcode_64Args"/>
     <event value="3044" symbol="task_0PCODE_64pcode_643044" version="0" task="task_0" opcode="opcode_64" level="win:Always" template="task_0PCODE_64pcode_64Args"/>
     <event value="3045" symbol="task_0PCODE_128pcode_1283045" version="0" task="task_0" opcode="opcode_128" level="win:Always" template="task_0PCODE_128pcode_1283045Args"/>
     <event value="3046" symbol="task_0PCODE_128pcode_1283046" version="0" task="task_0" opcode="opcode_128" level="win:Always" template="task_0PCODE_64pcode_64Args"/>
     <event value="3048" symbol="task_0PCODE_192pcode_1923048" version="0" task="task_0" opcode="opcode_192" level="win:Always" template="task_0PCODE_64pcode_64Args"/>
     <event value="3050" symbol="task_0PCODE_192pcode_1923050" version="0" task="task_0" opcode="opcode_192" level="win:Always" template="task_0PCODE_64pcode_64Args"/>
     <event value="3052" symbol="task_0PCODE_64pcode_643052" version="0" task="task_0" opcode="opcode_64" level="win:Always" template="task_0PCODE_64pcode_64Args"/>
     <event value="3053" symbol="task_0PCODE_128pcode_1283053" version="0" task="task_0" opcode="opcode_128" level="win:Always" template="task_0PCODE_64pcode_64Args"/>
     <event value="3054" symbol="task_0PCODE_128pcode_1283054" version="0" task="task_0" opcode="opcode_128" level="win:Always" template="task_0PCODE_64pcode_64Args"/>
     <event value="3055" symbol="task_0PCODE_128pcode_1283055" version="0" task="task_0" opcode="opcode_128" level="win:Always" template="task_0PCODE_64pcode_64Args"/>
     <event value="3056" symbol="task_0PCODE_128pcode_1283056" version="0" task="task_0" opcode="opcode_128" level="win:Always" template="task_0PCODE_64pcode_64Args"/>
     <event value="3057" symbol="task_0PCODE_192pcode_1923057" version="0" task="task_0" opcode="opcode_192" level="win:Always" template="task_0PCODE_192pcode_1923057Args"/>
     <event value="3058" symbol="task_0PCODE_192pcode_1923058" version="0" task="task_0" opcode="opcode_192" level="win:Always" template="task_0PCODE_64pcode_64Args"/>
     <event value="3059" symbol="task_0PCODE_192pcode_1923059" version="0" task="task_0" opcode="opcode_192" level="win:Always" template="task_0PCODE_64pcode_64Args"/>
     <event value="3060" symbol="task_0PCODE_64pcode_643060" version="0" task="task_0" opcode="opcode_64" level="win:Always" template="task_0PCODE_192pcode_1923027Args"/>
     <event value="3061" symbol="task_0PCODE_128pcode_1283061" version="0" task="task_0" opcode="opcode_128" level="win:Always" template="task_0PCODE_64pcode_64Args"/>
     <event value="3062" symbol="task_0PCODE_128pcode_1283062" version="0" task="task_0" opcode="opcode_128" level="win:Always" template="task_0PCODE_128pcode_1283062Args"/>
     <event value="3072" symbol="task_0PCODE_128pcode_1283072" version="0" task="task_0" opcode="opcode_128" level="win:Always" template="task_0PCODE_64pcode_64Args"/>
     <event value="3073" symbol="task_0PCODE_128pcode_1283073" version="0" task="task_0" opcode="opcode_128" level="win:Always" template="task_0PCODE_64pcode_64Args"/>
     <event value="3078" symbol="task_0PCODE_128pcode_1283078" version="0" task="task_0" opcode="opcode_128" level="win:Always" template="task_0PCODE_64pcode_64Args"/>
     <event value="3079" symbol="task_0PCODE_192pcode_1923079" version="0" task="task_0" opcode="opcode_192" level="win:Always" template="task_0PCODE_192pcode_1923079Args"/>
     <event value="3083" symbol="task_0PCODE_192pcode_1923083" version="0" task="task_0" opcode="opcode_192" level="win:Always" template="task_0PCODE_192pcode_1923083Args"/>
     <event value="3084" symbol="task_0PCODE_192pcode_1923084" version="0" task="task_0" opcode="opcode_192" level="win:Always" template="task_0PCODE_192pcode_1923083Args"/>
     <event value="3085" symbol="task_0PCODE_192pcode_1923085" version="0" task="task_0" opcode="opcode_192" level="win:Always" template="task_0PCODE_64pcode_64Args"/>
     <event value="3086" symbol="task_0PCODE_128pcode_1283086" version="0" task="task_0" opcode="opcode_128" level="win:Always" template="task_0PCODE_64pcode_64Args"/>
     <event value="3087" symbol="task_0PCODE_192pcode_1923087" version="0" task="task_0" opcode="opcode_192" level="win:Always" template="task_0PCODE_64pcode_64Args"/>
     <event value="3088" symbol="task_0PCODE_192pcode_1923088" version="0" task="task_0" opcode="opcode_192" level="win:Always" template="task_0PCODE_64pcode_64Args"/>
     <event value="3089" symbol="task_0PCODE_192pcode_1923089" version="0" task="task_0" opcode="opcode_192" level="win:Always" template="task_0PCODE_64pcode_64Args"/>
     <event value="3090" symbol="task_0PCODE_192pcode_1923090" version="0" task="task_0" opcode="opcode_192" level="win:Always" template="task_0PCODE_64pcode_64Args"/>
     <event value="3091" symbol="task_0PCODE_192pcode_1923091" version="0" task="task_0" opcode="opcode_192" level="win:Always" template="task_0PCODE_64pcode_64Args"/>
     <event value="3092" symbol="task_0PCODE_192pcode_1923092" version="0" task="task_0" opcode="opcode_192" level="win:Always" template="task_0PCODE_64pcode_64Args"/>
     <event value="3093" symbol="task_0PCODE_192pcode_1923093" version="0" task="task_0" opcode="opcode_192" level="win:Always" template="task_0PCODE_64pcode_64Args"/>
     <event value="3095" symbol="task_0PCODE_64pcode_643095" version="0" task="task_0" opcode="opcode_64" level="win:Always" template="task_0PCODE_64pcode_643095Args"/>
     <event value="3096" symbol="task_0PCODE_64pcode_643096" version="0" task="task_0" opcode="opcode_64" level="win:Always" template="task_0PCODE_64pcode_641004Args"/>
     <event value="3097" symbol="task_0PCODE_192pcode_1923097" version="0" task="task_0" opcode="opcode_192" level="win:Always" template="task_0PCODE_64pcode_64Args"/>
     <event value="3099" symbol="task_0PCODE_192pcode_1923099" version="0" task="task_0" opcode="opcode_192" level="win:Always" template="task_0PCODE_64pcode_64Args"/>
     <event value="3100" symbol="task_0PCODE_192pcode_1923100" version="0" task="task_0" opcode="opcode_192" level="win:Always" template="task_0PCODE_64pcode_64Args"/>
     <event value="3101" symbol="task_0PCODE_192pcode_1923101" version="0" task="task_0" opcode="opcode_192" level="win:Always"/>
     <event value="4103" symbol="task_0PCODE_64pcode_644103" version="0" task="task_0" opcode="opcode_64" level="win:Always" template="task_0PCODE_64pcode_644103Args"/>
     <event value="4104" symbol="task_0PCODE_64pcode_644104" version="0" task="task_0" opcode="opcode_64" level="win:Always" template="task_0PCODE_64pcode_644104Args"/>
     <event value="4105" symbol="task_0PCODE_192pcode_1924105" version="0" task="task_0" opcode="opcode_192" level="win:Always" template="task_0PCODE_64pcode_644104Args"/>
     <event value="4106" symbol="task_0PCODE_192pcode_1924106" version="0" task="task_0" opcode="opcode_192" level="win:Always" template="task_0PCODE_64pcode_644104Args"/>
     <event value="4121" symbol="task_0PCODE_64pcode_644121" version="0" task="task_0" opcode="opcode_64" level="win:Always" template="task_0PCODE_64pcode_644103Args"/>
     <event value="4138" symbol="task_0PCODE_64pcode_644138" version="0" task="task_0" opcode="opcode_64" level="win:Always" template="task_0PCODE_64pcode_644138Args"/>
     <event value="4163" symbol="task_0PCODE_64pcode_644163" version="0" task="task_0" opcode="opcode_64" level="win:Always" template="task_0PCODE_64pcode_644103Args"/>
     <event value="4164" symbol="task_0PCODE_64pcode_644164" version="0" task="task_0" opcode="opcode_64" level="win:Always" template="task_0PCODE_64pcode_644103Args"/>
     <event value="4165" symbol="task_0PCODE_64pcode_644165" version="0" task="task_0" opcode="opcode_64" level="win:Always" template="task_0PCODE_64pcode_644165Args"/>
     <event value="4166" symbol="task_0PCODE_64pcode_644166" version="0" task="task_0" opcode="opcode_64" level="win:Always" template="task_0PCODE_64pcode_644166Args"/>
     <event value="4167" symbol="task_0PCODE_64pcode_644167" version="0" task="task_0" opcode="opcode_64" level="win:Always" template="task_0PCODE_64pcode_644167Args"/>
     <event value="4168" symbol="task_0PCODE_128pcode_1284168" version="0" task="task_0" opcode="opcode_128" level="win:Always" template="task_0PCODE_128pcode_1284168Args"/>
     <event value="4169" symbol="task_0PCODE_128pcode_1284169" version="0" task="task_0" opcode="opcode_128" level="win:Always" template="task_0PCODE_128pcode_1284169Args"/>
     <event value="7001" symbol="task_0PCODE_192pcode_1927001" version="0" task="task_0" opcode="opcode_192" level="win:Always" template="task_0PCODE_192pcode_1927001Args"/>
     <event value="7010" symbol="task_0PCODE_192pcode_1927010" version="0" task="task_0" opcode="opcode_192" level="win:Always" template="task_0PCODE_64pcode_64Args"/>
     <event value="7011" symbol="task_0PCODE_192pcode_1927011" version="0" task="task_0" opcode="opcode_192" level="win:Always" template="task_0PCODE_192pcode_1927011Args"/>
     <event value="7013" symbol="task_0PCODE_192pcode_1927013" version="0" task="task_0" opcode="opcode_192" level="win:Always" template="task_0PCODE_192pcode_1927011Args"/>
     <event value="7040" symbol="task_0PCODE_192pcode_1927040" version="0" task="task_0" opcode="opcode_192" level="win:Always" template="task_0PCODE_192pcode_1927040Args"/>
     <event value="7042" symbol="task_0PCODE_64pcode_647042" version="0" task="task_0" opcode="opcode_64" level="win:Always" template="task_0PCODE_64pcode_641004Args"/>
     <event value="7043" symbol="task_0PCODE_192pcode_1927043" version="0" task="task_0" opcode="opcode_192" level="win:Always" template="task_0PCODE_64pcode_64Args"/>
     <event value="7064" symbol="task_0PCODE_192pcode_1927064" version="0" task="task_0" opcode="opcode_192" level="win:Always" template="task_0PCODE_64pcode_64Args"/>
     <event value="7066" symbol="task_0PCODE_192pcode_1927066" version="0" task="task_0" opcode="opcode_192" level="win:Always" template="task_0PCODE_192pcode_1927011Args"/>
     <event value="7068" symbol="task_0PCODE_192pcode_1927068" version="0" task="task_0" opcode="opcode_192" level="win:Always" template="task_0PCODE_64pcode_64Args"/>
     <event value="7070" symbol="task_0PCODE_192pcode_1927070" version="0" task="task_0" opcode="opcode_192" level="win:Always" template="task_0PCODE_64pcode_64Args"/>
     <event value="7071" symbol="task_0PCODE_192pcode_1927071" version="0" task="task_0" opcode="opcode_192" level="win:Always" template="task_0PCODE_64pcode_64Args"/>
     <event value="9000" symbol="task_0PCODE_192pcode_1929000" version="0" task="task_0" opcode="opcode_192" level="win:Always" template="task_0PCODE_64pcode_64Args"/>
     <event value="9001" symbol="task_0PCODE_192pcode_1929001" version="0" task="task_0" opcode="opcode_192" level="win:Always" template="task_0PCODE_64pcode_64Args"/>
     <event value="9002" symbol="task_0PCODE_192pcode_1929002" version="0" task="task_0" opcode="opcode_192" level="win:Always" template="task_0PCODE_64pcode_64Args"/>
     <event value="9003" symbol="task_0PCODE_128pcode_1289003" version="0" task="task_0" opcode="opcode_128" level="win:Always" template="task_0PCODE_64pcode_64Args"/>
     <event value="10013" symbol="task_0PCODE_128pcode_12810013" version="0" task="task_0" opcode="opcode_128" level="win:Always" template="task_0PCODE_64pcode_64Args"/>
     <event value="10014" symbol="task_0PCODE_128pcode_12810014" version="0" task="task_0" opcode="opcode_128" level="win:Always" template="task_0PCODE_128pcode_12810014Args"/>
     <event value="10020" symbol="task_0PCODE_128pcode_12810020" version="0" task="task_0" opcode="opcode_128" level="win:Always" template="task_0PCODE_128pcode_12810020Args"/>
     <event value="10021" symbol="task_0PCODE_128pcode_12810021" version="0" task="task_0" opcode="opcode_128" level="win:Always" template="task_0PCODE_128pcode_12810020Args"/>
     <event value="10022" symbol="task_0PCODE_128pcode_12810022" version="0" task="task_0" opcode="opcode_128" level="win:Always" template="task_0PCODE_128pcode_12810022Args"/>
     <event value="10023" symbol="task_0PCODE_128pcode_12810023" version="0" task="task_0" opcode="opcode_128" level="win:Always" template="task_0PCODE_128pcode_12810023Args"/>
     <event value="10024" symbol="task_0PCODE_128pcode_12810024" version="0" task="task_0" opcode="opcode_128" level="win:Always" template="task_0PCODE_128pcode_12810024Args"/>
    </events>
    <templates>
     <template tid="task_0PCODE_64pcode_64Args">
      <data name="ExtraInfo" inType="win:UnicodeString"/>
     </template>
     <template tid="task_0PCODE_64pcode_641004Args">
      <data name="ExtraInfo" inType="win:UnicodeString"/>
      <data name="Reason" inType="win:UnicodeString"/>
     </template>
     <template tid="task_0PCODE_192pcode_192Args">
      <data name="ExtraInfo" inType="win:UnicodeString"/>
      <data name="Phase" inType="win:UnicodeString"/>
      <data name="HR" inType="win:UnicodeString"/>
      <data name="DiagnosticsInfo" inType="win:UnicodeString"/>
     </template>
     <template tid="task_0PCODE_192pcode_1921009Args">
      <data name="ExtraInfo" inType="win:UnicodeString"/>
      <data name="Address" inType="win:UnicodeString"/>
     </template>
     <template tid="task_0PCODE_192pcode_1921011Args">
      <data name="ExtraInfo" inType="win:UnicodeString"/>
      <data name="Phase" inType="win:UnicodeString"/>
      <data name="HR" inType="win:UnicodeString"/>
     </template>
     <template tid="task_0PCODE_128pcode_1281014Args">
      <data name="ExtraInfo" inType="win:UnicodeString"/>
      <data name="DebugInfo" inType="win:UnicodeString"/>
     </template>
     <template tid="task_0PCODE_128pcode_1281015Args">
      <data name="ExtraInfo" inType="win:UnicodeString"/>
      <data name="EventID" inType="win:UnicodeString"/>
      <data name="RepeatCount" inType="win:UnicodeString"/>
      <data name="ReferenceTime" inType="win:UnicodeString"/>
     </template>
     <template tid="task_0PCODE_192pcode_1921016Args">
      <data name="ExtraInfo" inType="win:UnicodeString"/>
      <data name="OldIndexPath" inType="win:UnicodeString"/>
      <data name="NewIndexPath" inType="win:UnicodeString"/>
      <data name="Phase" inType="win:UnicodeString"/>
      <data name="ErrorCode" inType="win:UnicodeString"/>
     </template>
     <template tid="task_0PCODE_64pcode_641017Args">
      <data name="ExtraInfo" inType="win:UnicodeString"/>
      <data name="OldIndexPath" inType="win:UnicodeString"/>
      <data name="NewIndexPath" inType="win:UnicodeString"/>
     </template>
     <template tid="task_0PCODE_192pcode_1921019Args">
      <data name="ExtraInfo" inType="win:UnicodeString"/>
      <data name="Phase" inType="win:UnicodeString"/>
      <data name="ErrorCode" inType="win:UnicodeString"/>
      <data name="Path" inType="win:UnicodeString"/>
     </template>
     <template tid="task_0PCODE_128pcode_1281044Args">
      <data name="ExtraInfo" inType="win:UnicodeString"/>
      <data name="FileName" inType="win:UnicodeString"/>
     </template>
     <template tid="task_0PCODE_128pcode_1281053Args">
      <data name="Code" inType="win:UnicodeString"/>
      <data name="StackTrace" inType="win:UnicodeString"/>
     </template>
     <template tid="task_0PCODE_192pcode_1923008Args">
      <data name="ExtraInfo" inType="win:UnicodeString"/>
      <data name="Entry" inType="win:UnicodeString"/>
     </template>
     <template tid="task_0PCODE_192pcode_1923010Args">
      <data name="ExtraInfo" inType="win:UnicodeString"/>
      <data name="FilePath" inType="win:UnicodeString"/>
     </template>
     <template tid="task_0PCODE_192pcode_1923014Args">
      <data name="ExtraInfo" inType="win:UnicodeString"/>
      <data name="ID" inType="win:UnicodeString"/>
     </template>
     <template tid="task_0PCODE_192pcode_1923020Args">
      <data name="ExtraInfo" inType="win:UnicodeString"/>
      <data name="ErrorCode" inType="win:UnicodeString"/>
     </template>
     <template tid="task_0PCODE_192pcode_1923027Args">
      <data name="ExtraInfo" inType="win:UnicodeString"/>
      <data name="URL" inType="win:UnicodeString"/>
     </template>
     <template tid="task_0PCODE_192pcode_1923029Args">
      <data name="ExtraInfo" inType="win:UnicodeString"/>
      <data name="Plugin" inType="win:UnicodeString"/>
     </template>
     <template tid="task_0PCODE_192pcode_1923034Args">
      <data name="ExtraInfo" inType="win:UnicodeString"/>
      <data name="ExpectedVersion" inType="win:UnicodeString"/>
     </template>
     <template tid="task_0PCODE_128pcode_1283038Args">
      <data name="ExtraInfo" inType="win:UnicodeString"/>
      <data name="RegPath" inType="win:UnicodeString"/>
     </template>
     <template tid="task_0PCODE_192pcode_1923040Args">
      <data name="ExtraInfo" inType="win:UnicodeString"/>
      <data name="RequestedStatusMessage" inType="win:UnicodeString"/>
     </template>
     <template tid="task_0PCODE_128pcode_1283045Args">
      <data name="ExtraInfo" inType="win:UnicodeString"/>
      <data name="OldLength" inType="win:UnicodeString"/>
      <data name="NewLength" inType="win:UnicodeString"/>
     </template>
     <template tid="task_0PCODE_192pcode_1923057Args">
      <data name="ExtraInfo" inType="win:UnicodeString"/>
      <data name="PluginManager" inType="win:UnicodeString"/>
     </template>
     <template tid="task_0PCODE_128pcode_1283062Args">
      <data name="ExtraInfo" inType="win:UnicodeString"/>
      <data name="Locale" inType="win:UnicodeString"/>
     </template>
     <template tid="task_0PCODE_192pcode_1923079Args">
      <data name="ExtraInfo" inType="win:UnicodeString"/>
      <data name="VolumeName" inType="win:UnicodeString"/>
     </template>
     <template tid="task_0PCODE_192pcode_1923083Args">
      <data name="ExtraInfo" inType="win:UnicodeString"/>
      <data name="ProtocolHandler" inType="win:UnicodeString"/>
      <data name="ErrorMessage" inType="win:UnicodeString"/>
     </template>
     <template tid="task_0PCODE_64pcode_643095Args">
      <data name="ExtraInfo" inType="win:UnicodeString"/>
      <data name="Domain" inType="win:UnicodeString"/>
      <data name="Account" inType="win:UnicodeString"/>
      <data name="Users" inType="win:UnicodeString"/>
      <data name="MaxUsers" inType="win:UnicodeString"/>
     </template>
     <template tid="task_0PCODE_64pcode_644103Args">
      <data name="ExtraInfo" inType="win:UnicodeString"/>
      <data name="CatalogName" inType="win:UnicodeString"/>
     </template>
     <template tid="task_0PCODE_64pcode_644104Args">
      <data name="ExtraInfo" inType="win:UnicodeString"/>
      <data name="CatalogName" inType="win:UnicodeString"/>
      <data name="ErrorMessage" inType="win:UnicodeString"/>
     </template>
     <template tid="task_0PCODE_64pcode_644138Args">
      <data name="ExtraInfo" inType="win:UnicodeString"/>
      <data name="Component" inType="win:UnicodeString"/>
      <data name="CatalogName" inType="win:UnicodeString"/>
     </template>
     <template tid="task_0PCODE_64pcode_644165Args">
      <data name="ExtraInfo" inType="win:UnicodeString"/>
      <data name="CatalogName" inType="win:UnicodeString"/>
      <data name="IndexesPerMergeLevel" inType="win:UnicodeString"/>
      <data name="__binLength" inType="win:UInt32"/>
      <data name="binary" inType="win:Binary" length="__binLength"/>
     </template>
     <template tid="task_0PCODE_64pcode_644166Args">
      <data name="ExtraInfo" inType="win:UnicodeString"/>
      <data name="CatalogName" inType="win:UnicodeString"/>
      <data name="ExpectedDocCount" inType="win:UnicodeString"/>
      <data name="__binLength" inType="win:UInt32"/>
      <data name="binary" inType="win:Binary" length="__binLength"/>
     </template>
     <template tid="task_0PCODE_64pcode_644167Args">
      <data name="ExtraInfo" inType="win:UnicodeString"/>
      <data name="CatalogName" inType="win:UnicodeString"/>
      <data name="MasterMergeReason" inType="win:UnicodeString"/>
      <data name="__binLength" inType="win:UInt32"/>
      <data name="binary" inType="win:Binary" length="__binLength"/>
     </template>
     <template tid="task_0PCODE_128pcode_1284168Args">
      <data name="ExtraInfo" inType="win:UnicodeString"/>
      <data name="ErrorMessage" inType="win:UnicodeString"/>
      <data name="__binLength" inType="win:UInt32"/>
      <data name="binary" inType="win:Binary" length="__binLength"/>
     </template>
     <template tid="task_0PCODE_128pcode_1284169Args">
      <data name="ExtraInfo" inType="win:UnicodeString"/>
      <data name="Phase" inType="win:UnicodeString"/>
     </template>
     <template tid="task_0PCODE_192pcode_1927001Args">
      <data name="ExtraInfo" inType="win:UnicodeString"/>
      <data name="SrcFile" inType="win:UnicodeString"/>
      <data name="DstFile" inType="win:UnicodeString"/>
     </template>
     <template tid="task_0PCODE_192pcode_1927011Args">
      <data name="ExtraInfo" inType="win:UnicodeString"/>
      <data name="Directory" inType="win:UnicodeString"/>
     </template>
     <template tid="task_0PCODE_192pcode_1927040Args">
      <data name="ExtraInfo" inType="win:UnicodeString"/>
      <data name="CorruptionId" inType="win:UnicodeString"/>
     </template>
     <template tid="task_0PCODE_128pcode_12810014Args">
      <data name="ExtraInfo" inType="win:UnicodeString"/>
      <data name="OldNoiseFile" inType="win:UnicodeString"/>
      <data name="NewNoiseFile" inType="win:UnicodeString"/>
     </template>
     <template tid="task_0PCODE_128pcode_12810020Args">
      <data name="Driver" inType="win:UnicodeString"/>
      <data name="InstanceName" inType="win:UnicodeString"/>
      <data name="InstanceNum" inType="win:UnicodeString"/>
      <data name="ErrorMessage" inType="win:UnicodeString"/>
     </template>
     <template tid="task_0PCODE_128pcode_12810022Args">
      <data name="Driver" inType="win:UnicodeString"/>
      <data name="InstanceName" inType="win:UnicodeString"/>
      <data name="InstanceNum" inType="win:UnicodeString"/>
     </template>
     <template tid="task_0PCODE_128pcode_12810023Args">
      <data name="ExtraInfo" inType="win:UnicodeString"/>
      <data name="ProtocolHostProcessID" inType="win:UnicodeString"/>
      <data name="FilterHostProcessID" inType="win:UnicodeString"/>
     </template>
     <template tid="task_0PCODE_128pcode_12810024Args">
      <data name="ExtraInfo" inType="win:UnicodeString"/>
      <data name="FilterHostProcessID" inType="win:UnicodeString"/>
     </template>
    </templates>
   </provider>
  </events>
 </instrumentation>
 <localization>
  <resources culture="en-US">
   <stringTable>
    <string id="task_task_0" value="task_0"/>
    <string id="opcode_task_0opcode_64" value="opcode_64"/>
    <string id="opcode_task_0opcode_128" value="opcode_128"/>
    <string id="opcode_task_0opcode_192" value="opcode_192"/>
   </stringTable>
  </resources>
 </localization>
</instrumentationManifest>
